LICENSE
setup.py
focusgployer/__init__.py
focusgployer/deployer.py
focusgployer.egg-info/PKG-INFO
focusgployer.egg-info/SOURCES.txt
focusgployer.egg-info/dependency_links.txt
focusgployer.egg-info/requires.txt
focusgployer.egg-info/top_level.txt